{"flowContents":{"identifier":"f678c8a1-f6b2-3511-af3b-fc519af73329","instanceIdentifier":"0bf6179c-0188-1000-596b-793bf7ba1641","name":"NiFi_Template_XML_to_Flow_Definition_JSON","comments":"","position":{"x":536.0,"y":214.0},"processGroups":[],"remoteProcessGroups":[],"processors":[{"identifier":"dd0a61e3-9fca-3e9b-87dc-88f81598a530","instanceIdentifier":"c3b841af-68ec-3942-46a6-577396bd2e51","name":"Success 200","comments":"","position":{"x":-632.0,"y":120.0},"type":"org.apache.nifi.processors.standard.HandleHttpResponse","bundle":{"group":"org.apache.nifi","artifact":"nifi-standard-nar","version":"1.21.0"},"properties":{"HTTP Context Map":"90ca2642-6a24-3692-81c6-b846e6812ec0","Attributes to add to the HTTP Response (Regex)":null,"HTTP Status Code":"200"},"propertyDescriptors":{"HTTP Context Map":{"name":"HTTP Context Map","displayName":"HTTP Context Map","identifiesControllerService":true,"sensitive":false},"Attributes to add to the HTTP Response (Regex)":{"name":"Attributes to add to the HTTP Response (Regex)","displayName":"Attributes to add to the HTTP Response (Regex)","identifiesControllerService":false,"sensitive":false},"HTTP Status Code":{"name":"HTTP Status Code","displayName":"HTTP Status Code","identifiesControllerService":false,"sensitive":false}},"style":{"background-color":"#0af731"},"schedulingPeriod":"0 sec","schedulingStrategy":"TIMER_DRIVEN","executionNode":"ALL","penaltyDuration":"30 sec","yieldDuration":"1 sec","bulletinLevel":"WARN","runDurationMillis":0,"concurrentlySchedulableTaskCount":1,"autoTerminatedRelationships":["failure"],"scheduledState":"ENABLED","retryCount":10,"retriedRelationships":[],"backoffMechanism":"PENALIZE_FLOWFILE","maxBackoffPeriod":"10 mins","componentType":"PROCESSOR","groupIdentifier":"f678c8a1-f6b2-3511-af3b-fc519af73329"},{"identifier":"758905ef-61cd-3616-b7ce-06aa46452498","instanceIdentifier":"76850580-874e-32e2-67a3-135b4e8f69b2","name":"API port 8089","comments":"","position":{"x":-632.0,"y":-464.0},"type":"org.apache.nifi.processors.standard.HandleHttpRequest","bundle":{"group":"org.apache.nifi","artifact":"nifi-standard-nar","version":"1.21.0"},"properties":{"multipart-request-max-size":"1 MB","parameters-to-attributes":null,"Allow POST":"true","Hostname":null,"Default URL Character Set":"UTF-8","Allow DELETE":"false","Maximum Threads":"200","HTTP Protocols":"HTTP_1_1","Additional HTTP Methods":null,"container-queue-size":"50","HTTP Context Map":"90ca2642-6a24-3692-81c6-b846e6812ec0","multipart-read-buffer-size":"512 KB","SSL Context Service":null,"Allow OPTIONS":"false","Allowed Paths":null,"Allow GET":"false","Allow HEAD":"false","Listening Port":"8089","Client Authentication":"No Authentication","Allow PUT":"false"},"propertyDescriptors":{"multipart-request-max-size":{"name":"multipart-request-max-size","displayName":"Multipart Request Max Size","identifiesControllerService":false,"sensitive":false},"parameters-to-attributes":{"name":"parameters-to-attributes","displayName":"Parameters to Attributes List","identifiesControllerService":false,"sensitive":false},"Allow POST":{"name":"Allow POST","displayName":"Allow POST","identifiesControllerService":false,"sensitive":false},"Hostname":{"name":"Hostname","displayName":"Hostname","identifiesControllerService":false,"sensitive":false},"Default URL Character Set":{"name":"Default URL Character Set","displayName":"Default URL Character Set","identifiesControllerService":false,"sensitive":false},"Allow DELETE":{"name":"Allow DELETE","displayName":"Allow DELETE","identifiesControllerService":false,"sensitive":false},"Maximum Threads":{"name":"Maximum Threads","displayName":"Maximum Threads","identifiesControllerService":false,"sensitive":false},"HTTP Protocols":{"name":"HTTP Protocols","displayName":"HTTP Protocols","identifiesControllerService":false,"sensitive":false},"Additional HTTP Methods":{"name":"Additional HTTP Methods","displayName":"Additional HTTP Methods","identifiesControllerService":false,"sensitive":false},"container-queue-size":{"name":"container-queue-size","displayName":"Container Queue Size","identifiesControllerService":false,"sensitive":false},"HTTP Context Map":{"name":"HTTP Context Map","displayName":"HTTP Context Map","identifiesControllerService":true,"sensitive":false},"multipart-read-buffer-size":{"name":"multipart-read-buffer-size","displayName":"Multipart Read Buffer Size","identifiesControllerService":false,"sensitive":false},"SSL Context Service":{"name":"SSL Context Service","displayName":"SSL Context Service","identifiesControllerService":true,"sensitive":false},"Allow OPTIONS":{"name":"Allow OPTIONS","displayName":"Allow OPTIONS","identifiesControllerService":false,"sensitive":false},"Allowed Paths":{"name":"Allowed Paths","displayName":"Allowed Paths","identifiesControllerService":false,"sensitive":false},"Allow GET":{"name":"Allow GET","displayName":"Allow GET","identifiesControllerService":false,"sensitive":false},"Allow HEAD":{"name":"Allow HEAD","displayName":"Allow HEAD","identifiesControllerService":false,"sensitive":false},"Listening Port":{"name":"Listening Port","displayName":"Listening Port","identifiesControllerService":false,"sensitive":false},"Client Authentication":{"name":"Client Authentication","displayName":"Client Authentication","identifiesControllerService":false,"sensitive":false},"Allow PUT":{"name":"Allow PUT","displayName":"Allow PUT","identifiesControllerService":false,"sensitive":false}},"style":{"background-color":"#f2f5b6"},"schedulingPeriod":"0 sec","schedulingStrategy":"TIMER_DRIVEN","executionNode":"ALL","penaltyDuration":"30 sec","yieldDuration":"1 sec","bulletinLevel":"WARN","runDurationMillis":0,"concurrentlySchedulableTaskCount":1,"autoTerminatedRelationships":[],"scheduledState":"ENABLED","retryCount":10,"retriedRelationships":[],"backoffMechanism":"PENALIZE_FLOWFILE","maxBackoffPeriod":"10 mins","componentType":"PROCESSOR","groupIdentifier":"f678c8a1-f6b2-3511-af3b-fc519af73329"},{"identifier":"94a7d891-e122-3902-aca0-cd0efc3cf059","instanceIdentifier":"deb11062-5f58-36ee-53c9-013a090c181a","name":"Get ProcessGroupID","comments":"","position":{"x":584.0,"y":120.0},"type":"org.apache.nifi.processors.standard.EvaluateJsonPath","bundle":{"group":"org.apache.nifi","artifact":"nifi-standard-nar","version":"1.21.0"},"properties":{"Destination":"flowfile-attribute","Return Type":"auto-detect","Null Value Representation":"empty string","Path Not Found Behavior":"ignore","ProcessGroupId":"$.flow.processGroups[0].id"},"propertyDescriptors":{"Destination":{"name":"Destination","displayName":"Destination","identifiesControllerService":false,"sensitive":false},"Return Type":{"name":"Return Type","displayName":"Return Type","identifiesControllerService":false,"sensitive":false},"Null Value Representation":{"name":"Null Value Representation","displayName":"Null Value Representation","identifiesControllerService":false,"sensitive":false},"Path Not Found Behavior":{"name":"Path Not Found Behavior","displayName":"Path Not Found Behavior","identifiesControllerService":false,"sensitive":false},"ProcessGroupId":{"name":"ProcessGroupId","displayName":"ProcessGroupId","identifiesControllerService":false,"sensitive":false}},"style":{},"schedulingPeriod":"0 sec","schedulingStrategy":"TIMER_DRIVEN","executionNode":"ALL","penaltyDuration":"30 sec","yieldDuration":"1 sec","bulletinLevel":"WARN","runDurationMillis":0,"concurrentlySchedulableTaskCount":1,"autoTerminatedRelationships":["failure","unmatched"],"scheduledState":"ENABLED","retryCount":10,"retriedRelationships":[],"backoffMechanism":"PENALIZE_FLOWFILE","maxBackoffPeriod":"10 mins","componentType":"PROCESSOR","groupIdentifier":"f678c8a1-f6b2-3511-af3b-fc519af73329"},{"identifier":"0a153468-2149-3b96-b023-2a8b5d067896","instanceIdentifier":"3acf3a47-9225-1c28-56e5-d9a052eea7a0","name":"Get templateId","comments":"","position":{"x":584.0,"y":-456.0},"type":"org.apache.nifi.processors.standard.EvaluateXPath","bundle":{"group":"org.apache.nifi","artifact":"nifi-standard-nar","version":"1.21.0"},"properties":{"Destination":"flowfile-attribute","disconnectedNodeAcknowledged":"false","originX":"-818.0810180336048","Return Type":"auto-detect","originY":"1327.5175834604102","templateId":"/templateEntity/template/id","Validate DTD":"false"},"propertyDescriptors":{"Destination":{"name":"Destination","displayName":"Destination","identifiesControllerService":false,"sensitive":false},"disconnectedNodeAcknowledged":{"name":"disconnectedNodeAcknowledged","displayName":"disconnectedNodeAcknowledged","identifiesControllerService":false,"sensitive":false},"originX":{"name":"originX","displayName":"originX","identifiesControllerService":false,"sensitive":false},"Return Type":{"name":"Return Type","displayName":"Return Type","identifiesControllerService":false,"sensitive":false},"originY":{"name":"originY","displayName":"originY","identifiesControllerService":false,"sensitive":false},"templateId":{"name":"templateId","displayName":"templateId","identifiesControllerService":false,"sensitive":false},"Validate DTD":{"name":"Validate DTD","displayName":"Allow DTD","identifiesControllerService":false,"sensitive":false}},"style":{},"schedulingPeriod":"0 sec","schedulingStrategy":"TIMER_DRIVEN","executionNode":"ALL","penaltyDuration":"30 sec","yieldDuration":"1 sec","bulletinLevel":"WARN","runDurationMillis":0,"concurrentlySchedulableTaskCount":1,"autoTerminatedRelationships":["failure","unmatched"],"scheduledState":"ENABLED","retryCount":10,"retriedRelationships":[],"backoffMechanism":"PENALIZE_FLOWFILE","maxBackoffPeriod":"10 mins","componentType":"PROCESSOR","groupIdentifier":"f678c8a1-f6b2-3511-af3b-fc519af73329"},{"identifier":"4b05fb03-d3f0-3a36-b6ee-acb3a3cc63a7","instanceIdentifier":"c130e8e1-ff38-3add-ccf1-6534b7544e4c","name":"API Template Instance","comments":"","position":{"x":584.0,"y":-72.0},"type":"org.apache.nifi.processors.standard.InvokeHTTP","bundle":{"group":"org.apache.nifi","artifact":"nifi-standard-nar","version":"1.21.0"},"properties":{"Proxy Host":null,"Attributes to Send":null,"use-etag":"false","proxy-configuration-service":null,"Proxy Type":"http","cookie-strategy":"DISABLED","Connection Timeout":"5 secs","send-message-body":"true","set-form-filename":"true","Always Output Response":"false","etag-max-cache-size":"10MB","Content-Encoding":"DISABLED","disable-http2":"False","idle-timeout":"5 mins","Put Response Body In Attribute":null,"Use Chunked Encoding":"false","Follow Redirects":"True","Remote URL":"https://stevenmatison.com:8443/nifi-api/process-groups/0bf2a200-0188-1000-4e4d-660091e597e1/template-instance","form-body-form-name":null,"Content-Type":"${mime.type}","flow-file-naming-strategy":"RANDOM","max-idle-connections":"5","invokehttp-proxy-user":null,"Read Timeout":"15 secs","Max Length To Put In Attribute":"256","ignore-response-content":"false","Proxy Port":null,"SSL Context Service":"4abefab0-d05e-390b-9a1a-c8f1c3c3f768","Digest Authentication":"false","HTTP Method":"POST","Add Response Headers to Request":"false","oauth2-access-token-provider":null,"Basic Authentication Username":null,"Include Date Header":"True","Penalize on \"No Retry\"":"false","Useragent":null},"propertyDescriptors":{"Proxy Host":{"name":"Proxy Host","displayName":"Proxy Host","identifiesControllerService":false,"sensitive":false},"Attributes to Send":{"name":"Attributes to Send","displayName":"Request Header Attributes Pattern","identifiesControllerService":false,"sensitive":false},"use-etag":{"name":"use-etag","displayName":"Response Cache Enabled","identifiesControllerService":false,"sensitive":false},"proxy-configuration-service":{"name":"proxy-configuration-service","displayName":"Proxy Configuration Service","identifiesControllerService":true,"sensitive":false},"Proxy Type":{"name":"Proxy Type","displayName":"Proxy Type","identifiesControllerService":false,"sensitive":false},"Basic Authentication Password":{"name":"Basic Authentication Password","displayName":"Request Password","identifiesControllerService":false,"sensitive":true},"cookie-strategy":{"name":"cookie-strategy","displayName":"Response Cookie Strategy","identifiesControllerService":false,"sensitive":false},"Connection Timeout":{"name":"Connection Timeout","displayName":"Socket Connect Timeout","identifiesControllerService":false,"sensitive":false},"send-message-body":{"name":"send-message-body","displayName":"Request Body Enabled","identifiesControllerService":false,"sensitive":false},"set-form-filename":{"name":"set-form-filename","displayName":"Request Multipart Form-Data Filename Enabled","identifiesControllerService":false,"sensitive":false},"Always Output Response":{"name":"Always Output Response","displayName":"Response Generation Required","identifiesControllerService":false,"sensitive":false},"etag-max-cache-size":{"name":"etag-max-cache-size","displayName":"Response Cache Size","identifiesControllerService":false,"sensitive":false},"Content-Encoding":{"name":"Content-Encoding","displayName":"Request Content-Encoding","identifiesControllerService":false,"sensitive":false},"disable-http2":{"name":"disable-http2","displayName":"HTTP/2 Disabled","identifiesControllerService":false,"sensitive":false},"idle-timeout":{"name":"idle-timeout","displayName":"Socket Idle Timeout","identifiesControllerService":false,"sensitive":false},"Put Response Body In Attribute":{"name":"Put Response Body In Attribute","displayName":"Response Body Attribute Name","identifiesControllerService":false,"sensitive":false},"Use Chunked Encoding":{"name":"Use Chunked Encoding","displayName":"Request Chunked Transfer-Encoding Enabled","identifiesControllerService":false,"sensitive":false},"Follow Redirects":{"name":"Follow Redirects","displayName":"Response Redirects Enabled","identifiesControllerService":false,"sensitive":false},"Remote URL":{"name":"Remote URL","displayName":"HTTP URL","identifiesControllerService":false,"sensitive":false},"form-body-form-name":{"name":"form-body-form-name","displayName":"Request Multipart Form-Data Name","identifiesControllerService":false,"sensitive":false},"Content-Type":{"name":"Content-Type","displayName":"Request Content-Type","identifiesControllerService":false,"sensitive":false},"flow-file-naming-strategy":{"name":"flow-file-naming-strategy","displayName":"Response FlowFile Naming Strategy","identifiesControllerService":false,"sensitive":false},"max-idle-connections":{"name":"max-idle-connections","displayName":"Socket Idle Connections","identifiesControllerService":false,"sensitive":false},"invokehttp-proxy-user":{"name":"invokehttp-proxy-user","displayName":"Proxy Username","identifiesControllerService":false,"sensitive":false},"Read Timeout":{"name":"Read Timeout","displayName":"Socket Read Timeout","identifiesControllerService":false,"sensitive":false},"Max Length To Put In Attribute":{"name":"Max Length To Put In Attribute","displayName":"Response Body Attribute Size","identifiesControllerService":false,"sensitive":false},"invokehttp-proxy-password":{"name":"invokehttp-proxy-password","displayName":"Proxy Password","identifiesControllerService":false,"sensitive":true},"ignore-response-content":{"name":"ignore-response-content","displayName":"Response Body Ignored","identifiesControllerService":false,"sensitive":false},"Proxy Port":{"name":"Proxy Port","displayName":"Proxy Port","identifiesControllerService":false,"sensitive":false},"SSL Context Service":{"name":"SSL Context Service","displayName":"SSL Context Service","identifiesControllerService":true,"sensitive":false},"Digest Authentication":{"name":"Digest Authentication","displayName":"Request Digest Authentication Enabled","identifiesControllerService":false,"sensitive":false},"HTTP Method":{"name":"HTTP Method","displayName":"HTTP Method","identifiesControllerService":false,"sensitive":false},"Add Response Headers to Request":{"name":"Add Response Headers to Request","displayName":"Response Header Request Attributes Enabled","identifiesControllerService":false,"sensitive":false},"oauth2-access-token-provider":{"name":"oauth2-access-token-provider","displayName":"Request OAuth2 Access Token Provider","identifiesControllerService":true,"sensitive":false},"Basic Authentication Username":{"name":"Basic Authentication Username","displayName":"Request Username","identifiesControllerService":false,"sensitive":false},"Include Date Header":{"name":"Include Date Header","displayName":"Request Date Header Enabled","identifiesControllerService":false,"sensitive":false},"Penalize on \"No Retry\"":{"name":"Penalize on \"No Retry\"","displayName":"Request Failure Penalization Enabled","identifiesControllerService":false,"sensitive":false},"Useragent":{"name":"Useragent","displayName":"Request User-Agent","identifiesControllerService":false,"sensitive":false}},"style":{},"schedulingPeriod":"0 sec","schedulingStrategy":"TIMER_DRIVEN","executionNode":"ALL","penaltyDuration":"30 sec","yieldDuration":"1 sec","bulletinLevel":"WARN","runDurationMillis":0,"concurrentlySchedulableTaskCount":1,"autoTerminatedRelationships":["No Retry","Retry","Original","Failure"],"scheduledState":"ENABLED","retryCount":10,"retriedRelationships":[],"backoffMechanism":"PENALIZE_FLOWFILE","maxBackoffPeriod":"10 mins","componentType":"PROCESSOR","groupIdentifier":"f678c8a1-f6b2-3511-af3b-fc519af73329"},{"identifier":"a960ff69-aede-3b13-99d9-1c48aec9da69","instanceIdentifier":"3acf3a96-9225-1c28-a120-c3eb6ffc4a14","name":"Fail 500","comments":"","position":{"x":-24.0,"y":-272.0},"type":"org.apache.nifi.processors.standard.HandleHttpResponse","bundle":{"group":"org.apache.nifi","artifact":"nifi-standard-nar","version":"1.21.0"},"properties":{"HTTP Context Map":"90ca2642-6a24-3692-81c6-b846e6812ec0","Attributes to add to the HTTP Response (Regex)":null,"HTTP Status Code":"500"},"propertyDescriptors":{"HTTP Context Map":{"name":"HTTP Context Map","displayName":"HTTP Context Map","identifiesControllerService":true,"sensitive":false},"Attributes to add to the HTTP Response (Regex)":{"name":"Attributes to add to the HTTP Response (Regex)","displayName":"Attributes to add to the HTTP Response (Regex)","identifiesControllerService":false,"sensitive":false},"HTTP Status Code":{"name":"HTTP Status Code","displayName":"HTTP Status Code","identifiesControllerService":false,"sensitive":false}},"style":{"background-color":"#fa0505"},"schedulingPeriod":"0 sec","schedulingStrategy":"TIMER_DRIVEN","executionNode":"ALL","penaltyDuration":"30 sec","yieldDuration":"1 sec","bulletinLevel":"WARN","runDurationMillis":0,"concurrentlySchedulableTaskCount":1,"autoTerminatedRelationships":["success","failure"],"scheduledState":"ENABLED","retryCount":10,"retriedRelationships":[],"backoffMechanism":"PENALIZE_FLOWFILE","maxBackoffPeriod":"10 mins","componentType":"PROCESSOR","groupIdentifier":"f678c8a1-f6b2-3511-af3b-fc519af73329"},{"identifier":"a1fdcc28-7b08-3a34-ad27-ef3779ba251c","instanceIdentifier":"3acf3a98-9225-1c28-6198-44970f328ff7","name":"API Delete Process Group","comments":"","position":{"x":-32.0,"y":304.0},"type":"org.apache.nifi.processors.standard.InvokeHTTP","bundle":{"group":"org.apache.nifi","artifact":"nifi-standard-nar","version":"1.21.0"},"properties":{"Proxy Host":null,"Attributes to Send":null,"use-etag":"false","proxy-configuration-service":null,"Proxy Type":"http","cookie-strategy":"DISABLED","Connection Timeout":"5 secs","send-message-body":"true","set-form-filename":"true","Always Output Response":"false","etag-max-cache-size":"10MB","Content-Encoding":"DISABLED","disable-http2":"False","idle-timeout":"5 mins","Put Response Body In Attribute":null,"Use Chunked Encoding":"false","Follow Redirects":"True","Remote URL":"https://stevenmatison.com:8443/nifi-api/process-groups/${ProcessGroupId}/?version=0","form-body-form-name":null,"Content-Type":"${mime.type}","flow-file-naming-strategy":"RANDOM","max-idle-connections":"5","invokehttp-proxy-user":null,"Read Timeout":"15 secs","Max Length To Put In Attribute":"256","ignore-response-content":"false","Proxy Port":null,"SSL Context Service":"4abefab0-d05e-390b-9a1a-c8f1c3c3f768","Digest Authentication":"false","HTTP Method":"DELETE","Add Response Headers to Request":"false","oauth2-access-token-provider":null,"Basic Authentication Username":null,"Include Date Header":"True","Penalize on \"No Retry\"":"false","Useragent":null},"propertyDescriptors":{"Proxy Host":{"name":"Proxy Host","displayName":"Proxy Host","identifiesControllerService":false,"sensitive":false},"Attributes to Send":{"name":"Attributes to Send","displayName":"Request Header Attributes Pattern","identifiesControllerService":false,"sensitive":false},"use-etag":{"name":"use-etag","displayName":"Response Cache Enabled","identifiesControllerService":false,"sensitive":false},"proxy-configuration-service":{"name":"proxy-configuration-service","displayName":"Proxy Configuration Service","identifiesControllerService":true,"sensitive":false},"Proxy Type":{"name":"Proxy Type","displayName":"Proxy Type","identifiesControllerService":false,"sensitive":false},"Basic Authentication Password":{"name":"Basic Authentication Password","displayName":"Request Password","identifiesControllerService":false,"sensitive":true},"cookie-strategy":{"name":"cookie-strategy","displayName":"Response Cookie Strategy","identifiesControllerService":false,"sensitive":false},"Connection Timeout":{"name":"Connection Timeout","displayName":"Socket Connect Timeout","identifiesControllerService":false,"sensitive":false},"send-message-body":{"name":"send-message-body","displayName":"Request Body Enabled","identifiesControllerService":false,"sensitive":false},"set-form-filename":{"name":"set-form-filename","displayName":"Request Multipart Form-Data Filename Enabled","identifiesControllerService":false,"sensitive":false},"Always Output Response":{"name":"Always Output Response","displayName":"Response Generation Required","identifiesControllerService":false,"sensitive":false},"etag-max-cache-size":{"name":"etag-max-cache-size","displayName":"Response Cache Size","identifiesControllerService":false,"sensitive":false},"Content-Encoding":{"name":"Content-Encoding","displayName":"Request Content-Encoding","identifiesControllerService":false,"sensitive":false},"disable-http2":{"name":"disable-http2","displayName":"HTTP/2 Disabled","identifiesControllerService":false,"sensitive":false},"idle-timeout":{"name":"idle-timeout","displayName":"Socket Idle Timeout","identifiesControllerService":false,"sensitive":false},"Put Response Body In Attribute":{"name":"Put Response Body In Attribute","displayName":"Response Body Attribute Name","identifiesControllerService":false,"sensitive":false},"Use Chunked Encoding":{"name":"Use Chunked Encoding","displayName":"Request Chunked Transfer-Encoding Enabled","identifiesControllerService":false,"sensitive":false},"Follow Redirects":{"name":"Follow Redirects","displayName":"Response Redirects Enabled","identifiesControllerService":false,"sensitive":false},"Remote URL":{"name":"Remote URL","displayName":"HTTP URL","identifiesControllerService":false,"sensitive":false},"form-body-form-name":{"name":"form-body-form-name","displayName":"Request Multipart Form-Data Name","identifiesControllerService":false,"sensitive":false},"Content-Type":{"name":"Content-Type","displayName":"Request Content-Type","identifiesControllerService":false,"sensitive":false},"flow-file-naming-strategy":{"name":"flow-file-naming-strategy","displayName":"Response FlowFile Naming Strategy","identifiesControllerService":false,"sensitive":false},"max-idle-connections":{"name":"max-idle-connections","displayName":"Socket Idle Connections","identifiesControllerService":false,"sensitive":false},"invokehttp-proxy-user":{"name":"invokehttp-proxy-user","displayName":"Proxy Username","identifiesControllerService":false,"sensitive":false},"Read Timeout":{"name":"Read Timeout","displayName":"Socket Read Timeout","identifiesControllerService":false,"sensitive":false},"Max Length To Put In Attribute":{"name":"Max Length To Put In Attribute","displayName":"Response Body Attribute Size","identifiesControllerService":false,"sensitive":false},"invokehttp-proxy-password":{"name":"invokehttp-proxy-password","displayName":"Proxy Password","identifiesControllerService":false,"sensitive":true},"ignore-response-content":{"name":"ignore-response-content","displayName":"Response Body Ignored","identifiesControllerService":false,"sensitive":false},"Proxy Port":{"name":"Proxy Port","displayName":"Proxy Port","identifiesControllerService":false,"sensitive":false},"SSL Context Service":{"name":"SSL Context Service","displayName":"SSL Context Service","identifiesControllerService":true,"sensitive":false},"Digest Authentication":{"name":"Digest Authentication","displayName":"Request Digest Authentication Enabled","identifiesControllerService":false,"sensitive":false},"HTTP Method":{"name":"HTTP Method","displayName":"HTTP Method","identifiesControllerService":false,"sensitive":false},"Add Response Headers to Request":{"name":"Add Response Headers to Request","displayName":"Response Header Request Attributes Enabled","identifiesControllerService":false,"sensitive":false},"oauth2-access-token-provider":{"name":"oauth2-access-token-provider","displayName":"Request OAuth2 Access Token Provider","identifiesControllerService":true,"sensitive":false},"Basic Authentication Username":{"name":"Basic Authentication Username","displayName":"Request Username","identifiesControllerService":false,"sensitive":false},"Include Date Header":{"name":"Include Date Header","displayName":"Request Date Header Enabled","identifiesControllerService":false,"sensitive":false},"Penalize on \"No Retry\"":{"name":"Penalize on \"No Retry\"","displayName":"Request Failure Penalization Enabled","identifiesControllerService":false,"sensitive":false},"Useragent":{"name":"Useragent","displayName":"Request User-Agent","identifiesControllerService":false,"sensitive":false}},"style":{},"schedulingPeriod":"0 sec","schedulingStrategy":"TIMER_DRIVEN","executionNode":"ALL","penaltyDuration":"30 sec","yieldDuration":"1 sec","bulletinLevel":"WARN","runDurationMillis":0,"concurrentlySchedulableTaskCount":1,"autoTerminatedRelationships":["No Retry","Retry","Original","Failure"],"scheduledState":"ENABLED","retryCount":10,"retriedRelationships":[],"backoffMechanism":"PENALIZE_FLOWFILE","maxBackoffPeriod":"10 mins","componentType":"PROCESSOR","groupIdentifier":"f678c8a1-f6b2-3511-af3b-fc519af73329"},{"identifier":"9cbae145-6820-3218-871b-3f64f48b99c1","instanceIdentifier":"3acf3a9d-9225-1c28-861d-015a427fa1be","name":"API Delete Template","comments":"","position":{"x":592.0,"y":304.0},"type":"org.apache.nifi.processors.standard.InvokeHTTP","bundle":{"group":"org.apache.nifi","artifact":"nifi-standard-nar","version":"1.21.0"},"properties":{"Proxy Host":null,"Attributes to Send":null,"use-etag":"false","proxy-configuration-service":null,"Proxy Type":"http","cookie-strategy":"DISABLED","Connection Timeout":"5 secs","send-message-body":"true","set-form-filename":"true","Always Output Response":"false","etag-max-cache-size":"10MB","Content-Encoding":"DISABLED","disable-http2":"False","idle-timeout":"5 mins","Put Response Body In Attribute":null,"Use Chunked Encoding":"false","Follow Redirects":"True","Remote URL":"https://stevenmatison.com:8443/nifi-api/templates/${templateId}","form-body-form-name":null,"Content-Type":"${mime.type}","flow-file-naming-strategy":"RANDOM","max-idle-connections":"5","invokehttp-proxy-user":null,"Read Timeout":"15 secs","Max Length To Put In Attribute":"256","ignore-response-content":"false","Proxy Port":null,"SSL Context Service":"4abefab0-d05e-390b-9a1a-c8f1c3c3f768","Digest Authentication":"false","HTTP Method":"DELETE","Add Response Headers to Request":"false","oauth2-access-token-provider":null,"Basic Authentication Username":null,"Include Date Header":"True","Penalize on \"No Retry\"":"false","Useragent":null},"propertyDescriptors":{"Proxy Host":{"name":"Proxy Host","displayName":"Proxy Host","identifiesControllerService":false,"sensitive":false},"Attributes to Send":{"name":"Attributes to Send","displayName":"Request Header Attributes Pattern","identifiesControllerService":false,"sensitive":false},"use-etag":{"name":"use-etag","displayName":"Response Cache Enabled","identifiesControllerService":false,"sensitive":false},"proxy-configuration-service":{"name":"proxy-configuration-service","displayName":"Proxy Configuration Service","identifiesControllerService":true,"sensitive":false},"Proxy Type":{"name":"Proxy Type","displayName":"Proxy Type","identifiesControllerService":false,"sensitive":false},"Basic Authentication Password":{"name":"Basic Authentication Password","displayName":"Request Password","identifiesControllerService":false,"sensitive":true},"cookie-strategy":{"name":"cookie-strategy","displayName":"Response Cookie Strategy","identifiesControllerService":false,"sensitive":false},"Connection Timeout":{"name":"Connection Timeout","displayName":"Socket Connect Timeout","identifiesControllerService":false,"sensitive":false},"send-message-body":{"name":"send-message-body","displayName":"Request Body Enabled","identifiesControllerService":false,"sensitive":false},"set-form-filename":{"name":"set-form-filename","displayName":"Request Multipart Form-Data Filename Enabled","identifiesControllerService":false,"sensitive":false},"Always Output Response":{"name":"Always Output Response","displayName":"Response Generation Required","identifiesControllerService":false,"sensitive":false},"etag-max-cache-size":{"name":"etag-max-cache-size","displayName":"Response Cache Size","identifiesControllerService":false,"sensitive":false},"Content-Encoding":{"name":"Content-Encoding","displayName":"Request Content-Encoding","identifiesControllerService":false,"sensitive":false},"disable-http2":{"name":"disable-http2","displayName":"HTTP/2 Disabled","identifiesControllerService":false,"sensitive":false},"idle-timeout":{"name":"idle-timeout","displayName":"Socket Idle Timeout","identifiesControllerService":false,"sensitive":false},"Put Response Body In Attribute":{"name":"Put Response Body In Attribute","displayName":"Response Body Attribute Name","identifiesControllerService":false,"sensitive":false},"Use Chunked Encoding":{"name":"Use Chunked Encoding","displayName":"Request Chunked Transfer-Encoding Enabled","identifiesControllerService":false,"sensitive":false},"Follow Redirects":{"name":"Follow Redirects","displayName":"Response Redirects Enabled","identifiesControllerService":false,"sensitive":false},"Remote URL":{"name":"Remote URL","displayName":"HTTP URL","identifiesControllerService":false,"sensitive":false},"form-body-form-name":{"name":"form-body-form-name","displayName":"Request Multipart Form-Data Name","identifiesControllerService":false,"sensitive":false},"Content-Type":{"name":"Content-Type","displayName":"Request Content-Type","identifiesControllerService":false,"sensitive":false},"flow-file-naming-strategy":{"name":"flow-file-naming-strategy","displayName":"Response FlowFile Naming Strategy","identifiesControllerService":false,"sensitive":false},"max-idle-connections":{"name":"max-idle-connections","displayName":"Socket Idle Connections","identifiesControllerService":false,"sensitive":false},"invokehttp-proxy-user":{"name":"invokehttp-proxy-user","displayName":"Proxy Username","identifiesControllerService":false,"sensitive":false},"Read Timeout":{"name":"Read Timeout","displayName":"Socket Read Timeout","identifiesControllerService":false,"sensitive":false},"Max Length To Put In Attribute":{"name":"Max Length To Put In Attribute","displayName":"Response Body Attribute Size","identifiesControllerService":false,"sensitive":false},"invokehttp-proxy-password":{"name":"invokehttp-proxy-password","displayName":"Proxy Password","identifiesControllerService":false,"sensitive":true},"ignore-response-content":{"name":"ignore-response-content","displayName":"Response Body Ignored","identifiesControllerService":false,"sensitive":false},"Proxy Port":{"name":"Proxy Port","displayName":"Proxy Port","identifiesControllerService":false,"sensitive":false},"SSL Context Service":{"name":"SSL Context Service","displayName":"SSL Context Service","identifiesControllerService":true,"sensitive":false},"Digest Authentication":{"name":"Digest Authentication","displayName":"Request Digest Authentication Enabled","identifiesControllerService":false,"sensitive":false},"HTTP Method":{"name":"HTTP Method","displayName":"HTTP Method","identifiesControllerService":false,"sensitive":false},"Add Response Headers to Request":{"name":"Add Response Headers to Request","displayName":"Response Header Request Attributes Enabled","identifiesControllerService":false,"sensitive":false},"oauth2-access-token-provider":{"name":"oauth2-access-token-provider","displayName":"Request OAuth2 Access Token Provider","identifiesControllerService":true,"sensitive":false},"Basic Authentication Username":{"name":"Basic Authentication Username","displayName":"Request Username","identifiesControllerService":false,"sensitive":false},"Include Date Header":{"name":"Include Date Header","displayName":"Request Date Header Enabled","identifiesControllerService":false,"sensitive":false},"Penalize on \"No Retry\"":{"name":"Penalize on \"No Retry\"","displayName":"Request Failure Penalization Enabled","identifiesControllerService":false,"sensitive":false},"Useragent":{"name":"Useragent","displayName":"Request User-Agent","identifiesControllerService":false,"sensitive":false}},"style":{},"schedulingPeriod":"0 sec","schedulingStrategy":"TIMER_DRIVEN","executionNode":"ALL","penaltyDuration":"30 sec","yieldDuration":"1 sec","bulletinLevel":"WARN","runDurationMillis":0,"concurrentlySchedulableTaskCount":1,"autoTerminatedRelationships":["Response","No Retry","Retry","Original","Failure"],"scheduledState":"ENABLED","retryCount":10,"retriedRelationships":[],"backoffMechanism":"PENALIZE_FLOWFILE","maxBackoffPeriod":"10 mins","componentType":"PROCESSOR","groupIdentifier":"f678c8a1-f6b2-3511-af3b-fc519af73329"},{"identifier":"0fc22c61-a197-3777-bbef-a4ae329f1cf0","instanceIdentifier":"d33740b5-d022-3817-aef8-ac1d1662da94","name":"API Upload Template","comments":"","position":{"x":-32.0,"y":-464.0},"type":"org.apache.nifi.processors.standard.InvokeHTTP","bundle":{"group":"org.apache.nifi","artifact":"nifi-standard-nar","version":"1.21.0"},"properties":{"Proxy Host":null,"Attributes to Send":null,"use-etag":"false","proxy-configuration-service":null,"Proxy Type":"http","cookie-strategy":"DISABLED","Connection Timeout":"50 secs","send-message-body":"true","set-form-filename":"true","Always Output Response":"false","etag-max-cache-size":"10MB","Content-Encoding":"DISABLED","disable-http2":"False","idle-timeout":"5 mins","Put Response Body In Attribute":null,"Use Chunked Encoding":"false","Follow Redirects":"True","Remote URL":"https://stevenmatison.com:8443/nifi-api/process-groups/0bf2a200-0188-1000-4e4d-660091e597e1/templates/upload","form-body-form-name":"template","Content-Type":"${mime.type}","flow-file-naming-strategy":"RANDOM","max-idle-connections":"5","invokehttp-proxy-user":null,"Read Timeout":"150 secs","Max Length To Put In Attribute":"256","ignore-response-content":"false","Proxy Port":null,"SSL Context Service":"4abefab0-d05e-390b-9a1a-c8f1c3c3f768","Digest Authentication":"false","HTTP Method":"POST","Add Response Headers to Request":"false","oauth2-access-token-provider":null,"Basic Authentication Username":null,"Include Date Header":"True","Penalize on \"No Retry\"":"false","Useragent":null},"propertyDescriptors":{"Proxy Host":{"name":"Proxy Host","displayName":"Proxy Host","identifiesControllerService":false,"sensitive":false},"Attributes to Send":{"name":"Attributes to Send","displayName":"Request Header Attributes Pattern","identifiesControllerService":false,"sensitive":false},"use-etag":{"name":"use-etag","displayName":"Response Cache Enabled","identifiesControllerService":false,"sensitive":false},"proxy-configuration-service":{"name":"proxy-configuration-service","displayName":"Proxy Configuration Service","identifiesControllerService":true,"sensitive":false},"Proxy Type":{"name":"Proxy Type","displayName":"Proxy Type","identifiesControllerService":false,"sensitive":false},"Basic Authentication Password":{"name":"Basic Authentication Password","displayName":"Request Password","identifiesControllerService":false,"sensitive":true},"cookie-strategy":{"name":"cookie-strategy","displayName":"Response Cookie Strategy","identifiesControllerService":false,"sensitive":false},"Connection Timeout":{"name":"Connection Timeout","displayName":"Socket Connect Timeout","identifiesControllerService":false,"sensitive":false},"send-message-body":{"name":"send-message-body","displayName":"Request Body Enabled","identifiesControllerService":false,"sensitive":false},"set-form-filename":{"name":"set-form-filename","displayName":"Request Multipart Form-Data Filename Enabled","identifiesControllerService":false,"sensitive":false},"Always Output Response":{"name":"Always Output Response","displayName":"Response Generation Required","identifiesControllerService":false,"sensitive":false},"etag-max-cache-size":{"name":"etag-max-cache-size","displayName":"Response Cache Size","identifiesControllerService":false,"sensitive":false},"Content-Encoding":{"name":"Content-Encoding","displayName":"Request Content-Encoding","identifiesControllerService":false,"sensitive":false},"disable-http2":{"name":"disable-http2","displayName":"HTTP/2 Disabled","identifiesControllerService":false,"sensitive":false},"idle-timeout":{"name":"idle-timeout","displayName":"Socket Idle Timeout","identifiesControllerService":false,"sensitive":false},"Put Response Body In Attribute":{"name":"Put Response Body In Attribute","displayName":"Response Body Attribute Name","identifiesControllerService":false,"sensitive":false},"Use Chunked Encoding":{"name":"Use Chunked Encoding","displayName":"Request Chunked Transfer-Encoding Enabled","identifiesControllerService":false,"sensitive":false},"Follow Redirects":{"name":"Follow Redirects","displayName":"Response Redirects Enabled","identifiesControllerService":false,"sensitive":false},"Remote URL":{"name":"Remote URL","displayName":"HTTP URL","identifiesControllerService":false,"sensitive":false},"form-body-form-name":{"name":"form-body-form-name","displayName":"Request Multipart Form-Data Name","identifiesControllerService":false,"sensitive":false},"Content-Type":{"name":"Content-Type","displayName":"Request Content-Type","identifiesControllerService":false,"sensitive":false},"flow-file-naming-strategy":{"name":"flow-file-naming-strategy","displayName":"Response FlowFile Naming Strategy","identifiesControllerService":false,"sensitive":false},"max-idle-connections":{"name":"max-idle-connections","displayName":"Socket Idle Connections","identifiesControllerService":false,"sensitive":false},"invokehttp-proxy-user":{"name":"invokehttp-proxy-user","displayName":"Proxy Username","identifiesControllerService":false,"sensitive":false},"Read Timeout":{"name":"Read Timeout","displayName":"Socket Read Timeout","identifiesControllerService":false,"sensitive":false},"Max Length To Put In Attribute":{"name":"Max Length To Put In Attribute","displayName":"Response Body Attribute Size","identifiesControllerService":false,"sensitive":false},"invokehttp-proxy-password":{"name":"invokehttp-proxy-password","displayName":"Proxy Password","identifiesControllerService":false,"sensitive":true},"ignore-response-content":{"name":"ignore-response-content","displayName":"Response Body Ignored","identifiesControllerService":false,"sensitive":false},"Proxy Port":{"name":"Proxy Port","displayName":"Proxy Port","identifiesControllerService":false,"sensitive":false},"SSL Context Service":{"name":"SSL Context Service","displayName":"SSL Context Service","identifiesControllerService":true,"sensitive":false},"Digest Authentication":{"name":"Digest Authentication","displayName":"Request Digest Authentication Enabled","identifiesControllerService":false,"sensitive":false},"HTTP Method":{"name":"HTTP Method","displayName":"HTTP Method","identifiesControllerService":false,"sensitive":false},"Add Response Headers to Request":{"name":"Add Response Headers to Request","displayName":"Response Header Request Attributes Enabled","identifiesControllerService":false,"sensitive":false},"oauth2-access-token-provider":{"name":"oauth2-access-token-provider","displayName":"Request OAuth2 Access Token Provider","identifiesControllerService":true,"sensitive":false},"Basic Authentication Username":{"name":"Basic Authentication Username","displayName":"Request Username","identifiesControllerService":false,"sensitive":false},"Include Date Header":{"name":"Include Date Header","displayName":"Request Date Header Enabled","identifiesControllerService":false,"sensitive":false},"Penalize on \"No Retry\"":{"name":"Penalize on \"No Retry\"","displayName":"Request Failure Penalization Enabled","identifiesControllerService":false,"sensitive":false},"Useragent":{"name":"Useragent","displayName":"Request User-Agent","identifiesControllerService":false,"sensitive":false}},"style":{},"schedulingPeriod":"0 sec","schedulingStrategy":"TIMER_DRIVEN","executionNode":"ALL","penaltyDuration":"30 sec","yieldDuration":"1 sec","bulletinLevel":"WARN","runDurationMillis":0,"concurrentlySchedulableTaskCount":1,"autoTerminatedRelationships":["Original"],"scheduledState":"ENABLED","retryCount":10,"retriedRelationships":[],"backoffMechanism":"PENALIZE_FLOWFILE","maxBackoffPeriod":"10 mins","componentType":"PROCESSOR","groupIdentifier":"f678c8a1-f6b2-3511-af3b-fc519af73329"},{"identifier":"a0d4a891-afed-313f-9c01-1946942c6fe5","instanceIdentifier":"3acf3a4e-9225-1c28-a80e-ff626a8f770d","name":"Build JSON Payload","comments":"","position":{"x":584.0,"y":-264.0},"type":"org.apache.nifi.processors.standard.AttributesToJSON","bundle":{"group":"org.apache.nifi","artifact":"nifi-standard-nar","version":"1.21.0"},"properties":{"attributes-to-json-regex":null,"Destination":"flowfile-content","Null Value":"false","Attributes List":"templateId,originX,originY,disconnectedNodeAcknowledged","Include Core Attributes":"false"},"propertyDescriptors":{"attributes-to-json-regex":{"name":"attributes-to-json-regex","displayName":"Attributes Regular Expression","identifiesControllerService":false,"sensitive":false},"Destination":{"name":"Destination","displayName":"Destination","identifiesControllerService":false,"sensitive":false},"Null Value":{"name":"Null Value","displayName":"Null Value","identifiesControllerService":false,"sensitive":false},"Attributes List":{"name":"Attributes List","displayName":"Attributes List","identifiesControllerService":false,"sensitive":false},"Include Core Attributes":{"name":"Include Core Attributes","displayName":"Include Core Attributes","identifiesControllerService":false,"sensitive":false}},"style":{},"schedulingPeriod":"0 sec","schedulingStrategy":"TIMER_DRIVEN","executionNode":"ALL","penaltyDuration":"30 sec","yieldDuration":"1 sec","bulletinLevel":"WARN","runDurationMillis":0,"concurrentlySchedulableTaskCount":1,"autoTerminatedRelationships":["failure"],"scheduledState":"ENABLED","retryCount":10,"retriedRelationships":[],"backoffMechanism":"PENALIZE_FLOWFILE","maxBackoffPeriod":"10 mins","componentType":"PROCESSOR","groupIdentifier":"f678c8a1-f6b2-3511-af3b-fc519af73329"},{"identifier":"221521c1-46e4-3a47-9bc6-debf9b61e253","instanceIdentifier":"ac1ef946-2c35-3abf-a5fd-46251bbe6a1b","name":"API Download Flow","comments":"","position":{"x":-32.0,"y":120.0},"type":"org.apache.nifi.processors.standard.InvokeHTTP","bundle":{"group":"org.apache.nifi","artifact":"nifi-standard-nar","version":"1.21.0"},"properties":{"Proxy Host":null,"Attributes to Send":null,"use-etag":"false","proxy-configuration-service":null,"Proxy Type":"http","cookie-strategy":"DISABLED","Connection Timeout":"5 secs","send-message-body":"true","set-form-filename":"true","Always Output Response":"false","etag-max-cache-size":"10MB","Content-Encoding":"DISABLED","disable-http2":"False","idle-timeout":"5 mins","Put Response Body In Attribute":null,"Use Chunked Encoding":"false","Follow Redirects":"True","Remote URL":"https://stevenmatison.com:8443/nifi-api/process-groups/${ProcessGroupId}/download","form-body-form-name":null,"Content-Type":"${mime.type}","flow-file-naming-strategy":"RANDOM","max-idle-connections":"5","invokehttp-proxy-user":null,"Read Timeout":"15 secs","Max Length To Put In Attribute":"256","ignore-response-content":"false","Proxy Port":null,"SSL Context Service":"4abefab0-d05e-390b-9a1a-c8f1c3c3f768","Digest Authentication":"false","HTTP Method":"GET","Add Response Headers to Request":"false","oauth2-access-token-provider":null,"Basic Authentication Username":null,"Include Date Header":"True","Penalize on \"No Retry\"":"false","Useragent":null},"propertyDescriptors":{"Proxy Host":{"name":"Proxy Host","displayName":"Proxy Host","identifiesControllerService":false,"sensitive":false},"Attributes to Send":{"name":"Attributes to Send","displayName":"Request Header Attributes Pattern","identifiesControllerService":false,"sensitive":false},"use-etag":{"name":"use-etag","displayName":"Response Cache Enabled","identifiesControllerService":false,"sensitive":false},"proxy-configuration-service":{"name":"proxy-configuration-service","displayName":"Proxy Configuration Service","identifiesControllerService":true,"sensitive":false},"Proxy Type":{"name":"Proxy Type","displayName":"Proxy Type","identifiesControllerService":false,"sensitive":false},"Basic Authentication Password":{"name":"Basic Authentication Password","displayName":"Request Password","identifiesControllerService":false,"sensitive":true},"cookie-strategy":{"name":"cookie-strategy","displayName":"Response Cookie Strategy","identifiesControllerService":false,"sensitive":false},"Connection Timeout":{"name":"Connection Timeout","displayName":"Socket Connect Timeout","identifiesControllerService":false,"sensitive":false},"send-message-body":{"name":"send-message-body","displayName":"Request Body Enabled","identifiesControllerService":false,"sensitive":false},"set-form-filename":{"name":"set-form-filename","displayName":"Request Multipart Form-Data Filename Enabled","identifiesControllerService":false,"sensitive":false},"Always Output Response":{"name":"Always Output Response","displayName":"Response Generation Required","identifiesControllerService":false,"sensitive":false},"etag-max-cache-size":{"name":"etag-max-cache-size","displayName":"Response Cache Size","identifiesControllerService":false,"sensitive":false},"Content-Encoding":{"name":"Content-Encoding","displayName":"Request Content-Encoding","identifiesControllerService":false,"sensitive":false},"disable-http2":{"name":"disable-http2","displayName":"HTTP/2 Disabled","identifiesControllerService":false,"sensitive":false},"idle-timeout":{"name":"idle-timeout","displayName":"Socket Idle Timeout","identifiesControllerService":false,"sensitive":false},"Put Response Body In Attribute":{"name":"Put Response Body In Attribute","displayName":"Response Body Attribute Name","identifiesControllerService":false,"sensitive":false},"Use Chunked Encoding":{"name":"Use Chunked Encoding","displayName":"Request Chunked Transfer-Encoding Enabled","identifiesControllerService":false,"sensitive":false},"Follow Redirects":{"name":"Follow Redirects","displayName":"Response Redirects Enabled","identifiesControllerService":false,"sensitive":false},"Remote URL":{"name":"Remote URL","displayName":"HTTP URL","identifiesControllerService":false,"sensitive":false},"form-body-form-name":{"name":"form-body-form-name","displayName":"Request Multipart Form-Data Name","identifiesControllerService":false,"sensitive":false},"Content-Type":{"name":"Content-Type","displayName":"Request Content-Type","identifiesControllerService":false,"sensitive":false},"flow-file-naming-strategy":{"name":"flow-file-naming-strategy","displayName":"Response FlowFile Naming Strategy","identifiesControllerService":false,"sensitive":false},"max-idle-connections":{"name":"max-idle-connections","displayName":"Socket Idle Connections","identifiesControllerService":false,"sensitive":false},"invokehttp-proxy-user":{"name":"invokehttp-proxy-user","displayName":"Proxy Username","identifiesControllerService":false,"sensitive":false},"Read Timeout":{"name":"Read Timeout","displayName":"Socket Read Timeout","identifiesControllerService":false,"sensitive":false},"Max Length To Put In Attribute":{"name":"Max Length To Put In Attribute","displayName":"Response Body Attribute Size","identifiesControllerService":false,"sensitive":false},"invokehttp-proxy-password":{"name":"invokehttp-proxy-password","displayName":"Proxy Password","identifiesControllerService":false,"sensitive":true},"ignore-response-content":{"name":"ignore-response-content","displayName":"Response Body Ignored","identifiesControllerService":false,"sensitive":false},"Proxy Port":{"name":"Proxy Port","displayName":"Proxy Port","identifiesControllerService":false,"sensitive":false},"SSL Context Service":{"name":"SSL Context Service","displayName":"SSL Context Service","identifiesControllerService":true,"sensitive":false},"Digest Authentication":{"name":"Digest Authentication","displayName":"Request Digest Authentication Enabled","identifiesControllerService":false,"sensitive":false},"HTTP Method":{"name":"HTTP Method","displayName":"HTTP Method","identifiesControllerService":false,"sensitive":false},"Add Response Headers to Request":{"name":"Add Response Headers to Request","displayName":"Response Header Request Attributes Enabled","identifiesControllerService":false,"sensitive":false},"oauth2-access-token-provider":{"name":"oauth2-access-token-provider","displayName":"Request OAuth2 Access Token Provider","identifiesControllerService":true,"sensitive":false},"Basic Authentication Username":{"name":"Basic Authentication Username","displayName":"Request Username","identifiesControllerService":false,"sensitive":false},"Include Date Header":{"name":"Include Date Header","displayName":"Request Date Header Enabled","identifiesControllerService":false,"sensitive":false},"Penalize on \"No Retry\"":{"name":"Penalize on \"No Retry\"","displayName":"Request Failure Penalization Enabled","identifiesControllerService":false,"sensitive":false},"Useragent":{"name":"Useragent","displayName":"Request User-Agent","identifiesControllerService":false,"sensitive":false}},"style":{},"schedulingPeriod":"0 sec","schedulingStrategy":"TIMER_DRIVEN","executionNode":"ALL","penaltyDuration":"30 sec","yieldDuration":"1 sec","bulletinLevel":"WARN","runDurationMillis":0,"concurrentlySchedulableTaskCount":1,"autoTerminatedRelationships":["No Retry","Retry","Original","Failure"],"scheduledState":"ENABLED","retryCount":10,"retriedRelationships":[],"backoffMechanism":"PENALIZE_FLOWFILE","maxBackoffPeriod":"10 mins","componentType":"PROCESSOR","groupIdentifier":"f678c8a1-f6b2-3511-af3b-fc519af73329"}],"inputPorts":[],"outputPorts":[],"connections":[{"identifier":"d17edcbb-5487-304a-af10-8a1a8e0c64e0","instanceIdentifier":"3acf3a57-9225-1c28-e8d8-41ffb7371a90","name":"","source":{"id":"221521c1-46e4-3a47-9bc6-debf9b61e253","type":"PROCESSOR","groupId":"f678c8a1-f6b2-3511-af3b-fc519af73329","name":"API Download Flow","comments":"","instanceIdentifier":"ac1ef946-2c35-3abf-a5fd-46251bbe6a1b"},"destination":{"id":"dd0a61e3-9fca-3e9b-87dc-88f81598a530","type":"PROCESSOR","groupId":"f678c8a1-f6b2-3511-af3b-fc519af73329","name":"Success 200","comments":"","instanceIdentifier":"c3b841af-68ec-3942-46a6-577396bd2e51"},"labelIndex":1,"zIndex":0,"selectedRelationships":["Response"],"backPressureObjectThreshold":10000,"backPressureDataSizeThreshold":"1 GB","flowFileExpiration":"0 sec","prioritizers":[],"bends":[],"loadBalanceStrategy":"DO_NOT_LOAD_BALANCE","partitioningAttribute":"","loadBalanceCompression":"DO_NOT_COMPRESS","componentType":"CONNECTION","groupIdentifier":"f678c8a1-f6b2-3511-af3b-fc519af73329"},{"identifier":"66e916a9-873d-3d88-9c18-b0fc9b2301db","instanceIdentifier":"e6b58260-de02-3d9d-119d-86e52329767c","name":"","source":{"id":"0fc22c61-a197-3777-bbef-a4ae329f1cf0","type":"PROCESSOR","groupId":"f678c8a1-f6b2-3511-af3b-fc519af73329","name":"API Upload Template","comments":"","instanceIdentifier":"d33740b5-d022-3817-aef8-ac1d1662da94"},"destination":{"id":"0a153468-2149-3b96-b023-2a8b5d067896","type":"PROCESSOR","groupId":"f678c8a1-f6b2-3511-af3b-fc519af73329","name":"Get templateId","comments":"","instanceIdentifier":"3acf3a47-9225-1c28-56e5-d9a052eea7a0"},"labelIndex":1,"zIndex":0,"selectedRelationships":["Response"],"backPressureObjectThreshold":10000,"backPressureDataSizeThreshold":"1 GB","flowFileExpiration":"0 sec","prioritizers":[],"bends":[],"loadBalanceStrategy":"DO_NOT_LOAD_BALANCE","partitioningAttribute":"","loadBalanceCompression":"DO_NOT_COMPRESS","componentType":"CONNECTION","groupIdentifier":"f678c8a1-f6b2-3511-af3b-fc519af73329"},{"identifier":"0234a395-5f41-3679-9c23-954129452094","instanceIdentifier":"3acf3a99-9225-1c28-659c-c237e2369e78","name":"","source":{"id":"dd0a61e3-9fca-3e9b-87dc-88f81598a530","type":"PROCESSOR","groupId":"f678c8a1-f6b2-3511-af3b-fc519af73329","name":"Success 200","comments":"","instanceIdentifier":"c3b841af-68ec-3942-46a6-577396bd2e51"},"destination":{"id":"a1fdcc28-7b08-3a34-ad27-ef3779ba251c","type":"PROCESSOR","groupId":"f678c8a1-f6b2-3511-af3b-fc519af73329","name":"API Delete Process Group","comments":"","instanceIdentifier":"3acf3a98-9225-1c28-6198-44970f328ff7"},"labelIndex":1,"zIndex":0,"selectedRelationships":["success"],"backPressureObjectThreshold":10000,"backPressureDataSizeThreshold":"1 GB","flowFileExpiration":"0 sec","prioritizers":[],"bends":[],"loadBalanceStrategy":"DO_NOT_LOAD_BALANCE","partitioningAttribute":"","loadBalanceCompression":"DO_NOT_COMPRESS","componentType":"CONNECTION","groupIdentifier":"f678c8a1-f6b2-3511-af3b-fc519af73329"},{"identifier":"476c2799-05e6-33be-b063-ca814d8bacfa","instanceIdentifier":"2e037a16-0211-3570-b719-10c939221555","name":"","source":{"id":"4b05fb03-d3f0-3a36-b6ee-acb3a3cc63a7","type":"PROCESSOR","groupId":"f678c8a1-f6b2-3511-af3b-fc519af73329","name":"API Template Instance","comments":"","instanceIdentifier":"c130e8e1-ff38-3add-ccf1-6534b7544e4c"},"destination":{"id":"94a7d891-e122-3902-aca0-cd0efc3cf059","type":"PROCESSOR","groupId":"f678c8a1-f6b2-3511-af3b-fc519af73329","name":"Get ProcessGroupID","comments":"","instanceIdentifier":"deb11062-5f58-36ee-53c9-013a090c181a"},"labelIndex":0,"zIndex":0,"selectedRelationships":["Response"],"backPressureObjectThreshold":10000,"backPressureDataSizeThreshold":"1 GB","flowFileExpiration":"0 sec","prioritizers":[],"bends":[],"loadBalanceStrategy":"DO_NOT_LOAD_BALANCE","partitioningAttribute":"","loadBalanceCompression":"DO_NOT_COMPRESS","componentType":"CONNECTION","groupIdentifier":"f678c8a1-f6b2-3511-af3b-fc519af73329"},{"identifier":"2aa125ab-badd-34a2-b0de-0e12fbb32c47","instanceIdentifier":"3acf3a8e-9225-1c28-17b5-5dc94a1ba191","name":"","source":{"id":"0fc22c61-a197-3777-bbef-a4ae329f1cf0","type":"PROCESSOR","groupId":"f678c8a1-f6b2-3511-af3b-fc519af73329","name":"API Upload Template","comments":"","instanceIdentifier":"d33740b5-d022-3817-aef8-ac1d1662da94"},"destination":{"id":"a960ff69-aede-3b13-99d9-1c48aec9da69","type":"PROCESSOR","groupId":"f678c8a1-f6b2-3511-af3b-fc519af73329","name":"Fail 500","comments":"","instanceIdentifier":"3acf3a96-9225-1c28-a120-c3eb6ffc4a14"},"labelIndex":1,"zIndex":0,"selectedRelationships":["No Retry","Retry","Failure"],"backPressureObjectThreshold":10000,"backPressureDataSizeThreshold":"1 GB","flowFileExpiration":"0 sec","prioritizers":[],"bends":[],"loadBalanceStrategy":"DO_NOT_LOAD_BALANCE","partitioningAttribute":"","loadBalanceCompression":"DO_NOT_COMPRESS","componentType":"CONNECTION","groupIdentifier":"f678c8a1-f6b2-3511-af3b-fc519af73329"},{"identifier":"ae2b0707-31d7-3c39-86c3-066f2812f06e","instanceIdentifier":"3acf3a9e-9225-1c28-501c-bcd93a6fefff","name":"","source":{"id":"a1fdcc28-7b08-3a34-ad27-ef3779ba251c","type":"PROCESSOR","groupId":"f678c8a1-f6b2-3511-af3b-fc519af73329","name":"API Delete Process Group","comments":"","instanceIdentifier":"3acf3a98-9225-1c28-6198-44970f328ff7"},"destination":{"id":"9cbae145-6820-3218-871b-3f64f48b99c1","type":"PROCESSOR","groupId":"f678c8a1-f6b2-3511-af3b-fc519af73329","name":"API Delete Template","comments":"","instanceIdentifier":"3acf3a9d-9225-1c28-861d-015a427fa1be"},"labelIndex":1,"zIndex":0,"selectedRelationships":["Response"],"backPressureObjectThreshold":10000,"backPressureDataSizeThreshold":"1 GB","flowFileExpiration":"0 sec","prioritizers":[],"bends":[],"loadBalanceStrategy":"DO_NOT_LOAD_BALANCE","partitioningAttribute":"","loadBalanceCompression":"DO_NOT_COMPRESS","componentType":"CONNECTION","groupIdentifier":"f678c8a1-f6b2-3511-af3b-fc519af73329"},{"identifier":"73ab599b-3010-37e9-be17-52957aeb9f89","instanceIdentifier":"3acf3a49-9225-1c28-6701-6841f7bdc693","name":"","source":{"id":"0a153468-2149-3b96-b023-2a8b5d067896","type":"PROCESSOR","groupId":"f678c8a1-f6b2-3511-af3b-fc519af73329","name":"Get templateId","comments":"","instanceIdentifier":"3acf3a47-9225-1c28-56e5-d9a052eea7a0"},"destination":{"id":"a0d4a891-afed-313f-9c01-1946942c6fe5","type":"PROCESSOR","groupId":"f678c8a1-f6b2-3511-af3b-fc519af73329","name":"Build JSON Payload","comments":"","instanceIdentifier":"3acf3a4e-9225-1c28-a80e-ff626a8f770d"},"labelIndex":1,"zIndex":0,"selectedRelationships":["matched"],"backPressureObjectThreshold":10000,"backPressureDataSizeThreshold":"1 GB","flowFileExpiration":"0 sec","prioritizers":[],"bends":[],"loadBalanceStrategy":"DO_NOT_LOAD_BALANCE","partitioningAttribute":"","loadBalanceCompression":"DO_NOT_COMPRESS","componentType":"CONNECTION","groupIdentifier":"f678c8a1-f6b2-3511-af3b-fc519af73329"},{"identifier":"9d20fdd8-2e9b-3411-b35f-7d22f0585912","instanceIdentifier":"31ddfff1-ea10-3f61-5bc0-2fad043a35ad","name":"","source":{"id":"94a7d891-e122-3902-aca0-cd0efc3cf059","type":"PROCESSOR","groupId":"f678c8a1-f6b2-3511-af3b-fc519af73329","name":"Get ProcessGroupID","comments":"","instanceIdentifier":"deb11062-5f58-36ee-53c9-013a090c181a"},"destination":{"id":"221521c1-46e4-3a47-9bc6-debf9b61e253","type":"PROCESSOR","groupId":"f678c8a1-f6b2-3511-af3b-fc519af73329","name":"API Download Flow","comments":"","instanceIdentifier":"ac1ef946-2c35-3abf-a5fd-46251bbe6a1b"},"labelIndex":1,"zIndex":0,"selectedRelationships":["matched"],"backPressureObjectThreshold":10000,"backPressureDataSizeThreshold":"1 GB","flowFileExpiration":"0 sec","prioritizers":[],"bends":[],"loadBalanceStrategy":"DO_NOT_LOAD_BALANCE","partitioningAttribute":"","loadBalanceCompression":"DO_NOT_COMPRESS","componentType":"CONNECTION","groupIdentifier":"f678c8a1-f6b2-3511-af3b-fc519af73329"},{"identifier":"402c99e2-5a3a-3628-964b-4885c7cb7005","instanceIdentifier":"3acf3a4f-9225-1c28-664c-d936c972ab36","name":"","source":{"id":"a0d4a891-afed-313f-9c01-1946942c6fe5","type":"PROCESSOR","groupId":"f678c8a1-f6b2-3511-af3b-fc519af73329","name":"Build JSON Payload","comments":"","instanceIdentifier":"3acf3a4e-9225-1c28-a80e-ff626a8f770d"},"destination":{"id":"4b05fb03-d3f0-3a36-b6ee-acb3a3cc63a7","type":"PROCESSOR","groupId":"f678c8a1-f6b2-3511-af3b-fc519af73329","name":"API Template Instance","comments":"","instanceIdentifier":"c130e8e1-ff38-3add-ccf1-6534b7544e4c"},"labelIndex":1,"zIndex":0,"selectedRelationships":["success"],"backPressureObjectThreshold":10000,"backPressureDataSizeThreshold":"1 GB","flowFileExpiration":"0 sec","prioritizers":[],"bends":[],"loadBalanceStrategy":"DO_NOT_LOAD_BALANCE","partitioningAttribute":"","loadBalanceCompression":"DO_NOT_COMPRESS","componentType":"CONNECTION","groupIdentifier":"f678c8a1-f6b2-3511-af3b-fc519af73329"},{"identifier":"5857c41b-87e8-3cd9-b621-a0f5cd115e8c","instanceIdentifier":"59ae135c-7598-3628-265d-25dbc6d024e9","name":"","source":{"id":"758905ef-61cd-3616-b7ce-06aa46452498","type":"PROCESSOR","groupId":"f678c8a1-f6b2-3511-af3b-fc519af73329","name":"API port 8089","comments":"","instanceIdentifier":"76850580-874e-32e2-67a3-135b4e8f69b2"},"destination":{"id":"0fc22c61-a197-3777-bbef-a4ae329f1cf0","type":"PROCESSOR","groupId":"f678c8a1-f6b2-3511-af3b-fc519af73329","name":"API Upload Template","comments":"","instanceIdentifier":"d33740b5-d022-3817-aef8-ac1d1662da94"},"labelIndex":1,"zIndex":0,"selectedRelationships":["success"],"backPressureObjectThreshold":10000,"backPressureDataSizeThreshold":"1 GB","flowFileExpiration":"0 sec","prioritizers":[],"bends":[],"loadBalanceStrategy":"DO_NOT_LOAD_BALANCE","partitioningAttribute":"","loadBalanceCompression":"DO_NOT_COMPRESS","componentType":"CONNECTION","groupIdentifier":"f678c8a1-f6b2-3511-af3b-fc519af73329"}],"labels":[],"funnels":[],"controllerServices":[{"identifier":"90ca2642-6a24-3692-81c6-b846e6812ec0","instanceIdentifier":"5dbf912a-13cf-3271-59ef-c840ab60cee2","name":"StandardHttpContextMap","comments":"","type":"org.apache.nifi.http.StandardHttpContextMap","bundle":{"group":"org.apache.nifi","artifact":"nifi-http-context-map-nar","version":"1.21.0"},"properties":{"Request Expiration":"1 min","Maximum Outstanding Requests":"5000"},"propertyDescriptors":{"Request Expiration":{"name":"Request Expiration","displayName":"Request Expiration","identifiesControllerService":false,"sensitive":false},"Maximum Outstanding Requests":{"name":"Maximum Outstanding Requests","displayName":"Maximum Outstanding Requests","identifiesControllerService":false,"sensitive":false}},"controllerServiceApis":[{"type":"org.apache.nifi.http.HttpContextMap","bundle":{"group":"org.apache.nifi","artifact":"nifi-standard-services-api-nar","version":"1.21.0"}}],"scheduledState":"DISABLED","bulletinLevel":"WARN","componentType":"CONTROLLER_SERVICE","groupIdentifier":"f678c8a1-f6b2-3511-af3b-fc519af73329"},{"identifier":"cc8a70f3-1b2b-320b-8a59-9e3296fb5f25","instanceIdentifier":"3acf3a46-9225-1c28-01fd-e6c1b249039f","name":"XMLReader","type":"org.apache.nifi.xml.XMLReader","bundle":{"group":"org.apache.nifi","artifact":"nifi-record-serialization-services-nar","version":"1.21.0"},"properties":{"content_field_name":null,"schema-branch":null,"Timestamp Format":null,"schema-inference-cache":null,"Date Format":null,"parse_xml_attributes":"true","record_format":"false","attribute_prefix":null,"schema-name":"${schema.name}","schema-registry":null,"Time Format":null,"schema-access-strategy":"infer-schema","schema-version":null,"schema-text":"${avro.schema}"},"propertyDescriptors":{"content_field_name":{"name":"content_field_name","displayName":"Field Name for Content","identifiesControllerService":false,"sensitive":false},"schema-branch":{"name":"schema-branch","displayName":"Schema Branch","identifiesControllerService":false,"sensitive":false},"Timestamp Format":{"name":"Timestamp Format","displayName":"Timestamp Format","identifiesControllerService":false,"sensitive":false},"schema-inference-cache":{"name":"schema-inference-cache","displayName":"Schema Inference Cache","identifiesControllerService":true,"sensitive":false},"Date Format":{"name":"Date Format","displayName":"Date Format","identifiesControllerService":false,"sensitive":false},"parse_xml_attributes":{"name":"parse_xml_attributes","displayName":"Parse XML Attributes","identifiesControllerService":false,"sensitive":false},"record_format":{"name":"record_format","displayName":"Expect Records as Array","identifiesControllerService":false,"sensitive":false},"attribute_prefix":{"name":"attribute_prefix","displayName":"Attribute Prefix","identifiesControllerService":false,"sensitive":false},"schema-name":{"name":"schema-name","displayName":"Schema Name","identifiesControllerService":false,"sensitive":false},"schema-registry":{"name":"schema-registry","displayName":"Schema Registry","identifiesControllerService":true,"sensitive":false},"Time Format":{"name":"Time Format","displayName":"Time Format","identifiesControllerService":false,"sensitive":false},"schema-access-strategy":{"name":"schema-access-strategy","displayName":"Schema Access Strategy","identifiesControllerService":false,"sensitive":false},"schema-version":{"name":"schema-version","displayName":"Schema Version","identifiesControllerService":false,"sensitive":false},"schema-text":{"name":"schema-text","displayName":"Schema Text","identifiesControllerService":false,"sensitive":false}},"controllerServiceApis":[{"type":"org.apache.nifi.serialization.RecordReaderFactory","bundle":{"group":"org.apache.nifi","artifact":"nifi-standard-services-api-nar","version":"1.21.0"}}],"scheduledState":"DISABLED","bulletinLevel":"WARN","componentType":"CONTROLLER_SERVICE","groupIdentifier":"f678c8a1-f6b2-3511-af3b-fc519af73329"},{"identifier":"b7d814c5-b451-3b99-bd19-67ec8116a6b0","instanceIdentifier":"3acf3a44-9225-1c28-4db7-71b616f337bf","name":"XMLReader","comments":"","type":"org.apache.nifi.xml.XMLReader","bundle":{"group":"org.apache.nifi","artifact":"nifi-record-serialization-services-nar","version":"1.21.0"},"properties":{"content_field_name":null,"schema-branch":null,"Timestamp Format":null,"schema-inference-cache":null,"Date Format":null,"parse_xml_attributes":"true","record_format":"false","attribute_prefix":null,"schema-name":"${schema.name}","schema-registry":null,"Time Format":null,"schema-access-strategy":"infer-schema","schema-version":null,"schema-text":"${avro.schema}"},"propertyDescriptors":{"content_field_name":{"name":"content_field_name","displayName":"Field Name for Content","identifiesControllerService":false,"sensitive":false},"schema-branch":{"name":"schema-branch","displayName":"Schema Branch","identifiesControllerService":false,"sensitive":false},"Timestamp Format":{"name":"Timestamp Format","displayName":"Timestamp Format","identifiesControllerService":false,"sensitive":false},"schema-inference-cache":{"name":"schema-inference-cache","displayName":"Schema Inference Cache","identifiesControllerService":true,"sensitive":false},"Date Format":{"name":"Date Format","displayName":"Date Format","identifiesControllerService":false,"sensitive":false},"parse_xml_attributes":{"name":"parse_xml_attributes","displayName":"Parse XML Attributes","identifiesControllerService":false,"sensitive":false},"record_format":{"name":"record_format","displayName":"Expect Records as Array","identifiesControllerService":false,"sensitive":false},"attribute_prefix":{"name":"attribute_prefix","displayName":"Attribute Prefix","identifiesControllerService":false,"sensitive":false},"schema-name":{"name":"schema-name","displayName":"Schema Name","identifiesControllerService":false,"sensitive":false},"schema-registry":{"name":"schema-registry","displayName":"Schema Registry","identifiesControllerService":true,"sensitive":false},"Time Format":{"name":"Time Format","displayName":"Time Format","identifiesControllerService":false,"sensitive":false},"schema-access-strategy":{"name":"schema-access-strategy","displayName":"Schema Access Strategy","identifiesControllerService":false,"sensitive":false},"schema-version":{"name":"schema-version","displayName":"Schema Version","identifiesControllerService":false,"sensitive":false},"schema-text":{"name":"schema-text","displayName":"Schema Text","identifiesControllerService":false,"sensitive":false}},"controllerServiceApis":[{"type":"org.apache.nifi.serialization.RecordReaderFactory","bundle":{"group":"org.apache.nifi","artifact":"nifi-standard-services-api-nar","version":"1.21.0"}}],"scheduledState":"DISABLED","bulletinLevel":"WARN","componentType":"CONTROLLER_SERVICE","groupIdentifier":"f678c8a1-f6b2-3511-af3b-fc519af73329"},{"identifier":"92d6864a-8d54-36b7-ae52-36bed95ca782","instanceIdentifier":"19ed0a31-6b6a-3b6e-5438-dccfddc50f15","name":"JsonPathReader","comments":"","type":"org.apache.nifi.json.JsonPathReader","bundle":{"group":"org.apache.nifi","artifact":"nifi-record-serialization-services-nar","version":"1.21.0"},"properties":{"Timestamp Format":null,"Date Format":null,"schema-branch":null,"schema-name":"${schema.name}","schema-registry":null,"templates":"$.templates","Time Format":null,"schema-access-strategy":"infer-schema","schema-version":null,"schema-text":"${avro.schema}"},"propertyDescriptors":{"Timestamp Format":{"name":"Timestamp Format","displayName":"Timestamp Format","identifiesControllerService":false,"sensitive":false},"Date Format":{"name":"Date Format","displayName":"Date Format","identifiesControllerService":false,"sensitive":false},"schema-branch":{"name":"schema-branch","displayName":"Schema Branch","identifiesControllerService":false,"sensitive":false},"schema-name":{"name":"schema-name","displayName":"Schema Name","identifiesControllerService":false,"sensitive":false},"schema-registry":{"name":"schema-registry","displayName":"Schema Registry","identifiesControllerService":true,"sensitive":false},"templates":{"name":"templates","displayName":"templates","identifiesControllerService":false,"sensitive":false},"Time Format":{"name":"Time Format","displayName":"Time Format","identifiesControllerService":false,"sensitive":false},"schema-access-strategy":{"name":"schema-access-strategy","displayName":"Schema Access Strategy","identifiesControllerService":false,"sensitive":false},"schema-version":{"name":"schema-version","displayName":"Schema Version","identifiesControllerService":false,"sensitive":false},"schema-text":{"name":"schema-text","displayName":"Schema Text","identifiesControllerService":false,"sensitive":false}},"controllerServiceApis":[{"type":"org.apache.nifi.serialization.RecordReaderFactory","bundle":{"group":"org.apache.nifi","artifact":"nifi-standard-services-api-nar","version":"1.21.0"}}],"scheduledState":"DISABLED","bulletinLevel":"WARN","componentType":"CONTROLLER_SERVICE","groupIdentifier":"f678c8a1-f6b2-3511-af3b-fc519af73329"},{"identifier":"0c146166-6a96-359d-9779-13d7746f0797","instanceIdentifier":"0c595d5d-0188-1000-4eee-460bddfe8291","name":"JsonTreeReader","comments":"","type":"org.apache.nifi.json.JsonTreeReader","bundle":{"group":"org.apache.nifi","artifact":"nifi-record-serialization-services-nar","version":"1.21.0"},"properties":{"schema-branch":null,"schema-application-strategy":"SELECTED_PART","Timestamp Format":null,"schema-inference-cache":null,"Date Format":null,"schema-name":"${schema.name}","starting-field-strategy":"ROOT_NODE","schema-registry":null,"starting-field-name":null,"Time Format":null,"schema-access-strategy":"infer-schema","schema-version":null,"schema-text":"${avro.schema}"},"propertyDescriptors":{"schema-branch":{"name":"schema-branch","displayName":"Schema Branch","identifiesControllerService":false,"sensitive":false},"schema-application-strategy":{"name":"schema-application-strategy","displayName":"Schema Application Strategy","identifiesControllerService":false,"sensitive":false},"Timestamp Format":{"name":"Timestamp Format","displayName":"Timestamp Format","identifiesControllerService":false,"sensitive":false},"schema-inference-cache":{"name":"schema-inference-cache","displayName":"Schema Inference Cache","identifiesControllerService":true,"sensitive":false},"Date Format":{"name":"Date Format","displayName":"Date Format","identifiesControllerService":false,"sensitive":false},"schema-name":{"name":"schema-name","displayName":"Schema Name","identifiesControllerService":false,"sensitive":false},"starting-field-strategy":{"name":"starting-field-strategy","displayName":"Starting Field Strategy","identifiesControllerService":false,"sensitive":false},"schema-registry":{"name":"schema-registry","displayName":"Schema Registry","identifiesControllerService":true,"sensitive":false},"starting-field-name":{"name":"starting-field-name","displayName":"Starting Field Name","identifiesControllerService":false,"sensitive":false},"Time Format":{"name":"Time Format","displayName":"Time Format","identifiesControllerService":false,"sensitive":false},"schema-access-strategy":{"name":"schema-access-strategy","displayName":"Schema Access Strategy","identifiesControllerService":false,"sensitive":false},"schema-version":{"name":"schema-version","displayName":"Schema Version","identifiesControllerService":false,"sensitive":false},"schema-text":{"name":"schema-text","displayName":"Schema Text","identifiesControllerService":false,"sensitive":false}},"controllerServiceApis":[{"type":"org.apache.nifi.serialization.RecordReaderFactory","bundle":{"group":"org.apache.nifi","artifact":"nifi-standard-services-api-nar","version":"1.21.0"}}],"scheduledState":"DISABLED","bulletinLevel":"WARN","componentType":"CONTROLLER_SERVICE","groupIdentifier":"f678c8a1-f6b2-3511-af3b-fc519af73329"},{"identifier":"669aa376-57fe-3f85-a7ac-7f361c0cc3fe","instanceIdentifier":"0c53da65-0188-1000-102e-e8c00964cb3f","name":"JsonRecordSetWriter","comments":"","type":"org.apache.nifi.json.JsonRecordSetWriter","bundle":{"group":"org.apache.nifi","artifact":"nifi-record-serialization-services-nar","version":"1.21.0"},"properties":{"schema-branch":null,"compression-level":"1","schema-cache":null,"Timestamp Format":null,"Date Format":null,"Pretty Print JSON":"false","compression-format":"none","Schema Write Strategy":"no-schema","suppress-nulls":"never-suppress","output-grouping":"output-array","schema-name":"${schema.name}","schema-registry":null,"Time Format":null,"schema-access-strategy":"inherit-record-schema","schema-protocol-version":"1","schema-version":null,"schema-text":"${avro.schema}"},"propertyDescriptors":{"schema-branch":{"name":"schema-branch","displayName":"Schema Branch","identifiesControllerService":false,"sensitive":false},"compression-level":{"name":"compression-level","displayName":"Compression Level","identifiesControllerService":false,"sensitive":false},"schema-cache":{"name":"schema-cache","displayName":"Schema Cache","identifiesControllerService":true,"sensitive":false},"Timestamp Format":{"name":"Timestamp Format","displayName":"Timestamp Format","identifiesControllerService":false,"sensitive":false},"Date Format":{"name":"Date Format","displayName":"Date Format","identifiesControllerService":false,"sensitive":false},"Pretty Print JSON":{"name":"Pretty Print JSON","displayName":"Pretty Print JSON","identifiesControllerService":false,"sensitive":false},"compression-format":{"name":"compression-format","displayName":"Compression Format","identifiesControllerService":false,"sensitive":false},"Schema Write Strategy":{"name":"Schema Write Strategy","displayName":"Schema Write Strategy","identifiesControllerService":false,"sensitive":false},"suppress-nulls":{"name":"suppress-nulls","displayName":"Suppress Null Values","identifiesControllerService":false,"sensitive":false},"output-grouping":{"name":"output-grouping","displayName":"Output Grouping","identifiesControllerService":false,"sensitive":false},"schema-name":{"name":"schema-name","displayName":"Schema Name","identifiesControllerService":false,"sensitive":false},"schema-registry":{"name":"schema-registry","displayName":"Schema Registry","identifiesControllerService":true,"sensitive":false},"Time Format":{"name":"Time Format","displayName":"Time Format","identifiesControllerService":false,"sensitive":false},"schema-access-strategy":{"name":"schema-access-strategy","displayName":"Schema Access Strategy","identifiesControllerService":false,"sensitive":false},"schema-protocol-version":{"name":"schema-protocol-version","displayName":"Schema Protocol Version","identifiesControllerService":false,"sensitive":false},"schema-version":{"name":"schema-version","displayName":"Schema Version","identifiesControllerService":false,"sensitive":false},"schema-text":{"name":"schema-text","displayName":"Schema Text","identifiesControllerService":false,"sensitive":false}},"controllerServiceApis":[{"type":"org.apache.nifi.serialization.RecordSetWriterFactory","bundle":{"group":"org.apache.nifi","artifact":"nifi-standard-services-api-nar","version":"1.21.0"}}],"scheduledState":"DISABLED","bulletinLevel":"WARN","componentType":"CONTROLLER_SERVICE","groupIdentifier":"f678c8a1-f6b2-3511-af3b-fc519af73329"}],"variables":{},"defaultFlowFileExpiration":"0 sec","defaultBackPressureObjectThreshold":10000,"defaultBackPressureDataSizeThreshold":"1 GB","componentType":"PROCESS_GROUP","flowFileConcurrency":"UNBOUNDED","flowFileOutboundPolicy":"STREAM_WHEN_AVAILABLE"},"externalControllerServices":{"4abefab0-d05e-390b-9a1a-c8f1c3c3f768":{"identifier":"4abefab0-d05e-390b-9a1a-c8f1c3c3f768","name":"StandardSSLContextService"}},"parameterContexts":{},"flowEncodingVersion":"1.0","parameterProviders":{},"latest":false}